MANIFEST.in
README.rst
setup.py
docs/HISTORY.txt
docs/INSTALL.txt
docs/LICENSE.GPL
docs/LICENSE.txt
docs/TODO.txt
unice/.DS_Store
unice/__init__.py
unice.portlet.vimeo.egg-info/PKG-INFO
unice.portlet.vimeo.egg-info/SOURCES.txt
unice.portlet.vimeo.egg-info/dependency_links.txt
unice.portlet.vimeo.egg-info/entry_points.txt
unice.portlet.vimeo.egg-info/namespace_packages.txt
unice.portlet.vimeo.egg-info/not-zip-safe
unice.portlet.vimeo.egg-info/requires.txt
unice.portlet.vimeo.egg-info/top_level.txt
unice/portlet/.DS_Store
unice/portlet/__init__.py
unice/portlet/vimeo/.DS_Store
unice/portlet/vimeo/__init__.py
unice/portlet/vimeo/configure.zcml
unice/portlet/vimeo/vimeoportlet.pt
unice/portlet/vimeo/vimeoportlet.py
unice/portlet/vimeo/vocabularies.py
unice/portlet/vimeo/browser/.DS_Store
unice/portlet/vimeo/browser/__init__.py
unice/portlet/vimeo/browser/configure.zcml
unice/portlet/vimeo/browser/javascripts/scripts.js
unice/portlet/vimeo/browser/stylesheets/styles.css
unice/portlet/vimeo/profiles/.DS_Store
unice/portlet/vimeo/profiles/default/cssregistry.xml
unice/portlet/vimeo/profiles/default/jsregistry.xml
unice/portlet/vimeo/profiles/default/metadata.xml
unice/portlet/vimeo/profiles/default/portlets.xml
unice/portlet/vimeo/tests/__init__.py
unice/portlet/vimeo/tests/base.py
unice/portlet/vimeo/tests/test_portlet.py